gutils/__init__.py
gutils/endpoints_helper.py
gutils/gamma_client.py
gutils/gitlab_client.py
gutils/misc.py
gutils/slack_client.py
gutils/tm4j_client.py
gutils/config/__init__.py
gutils/config/settings.py
gutils_python-1.1.5.dist-info/LICENSE
gutils_python-1.1.5.dist-info/METADATA
gutils_python-1.1.5.dist-info/WHEEL
gutils_python-1.1.5.dist-info/top_level.txt
gutils_python-1.1.5.dist-info/zip-safe
gutils_python-1.1.5.dist-info/RECORD
