Metadata-Version: 2.1
Name: gutils-python
Version: 1.1.5
Summary: Grab Utilities
Home-page: https://gitlab.myteksi.net/quality-assurance/doraemon
Author: chaofeng.ma
Author-email: chaofeng.ma@grabtaxi.com
Classifier: Programming Language :: Python :: 3
Classifier: License :: OSI Approved :: MIT License
Classifier: Operating System :: OS Independent
License-File: LICENSE
Requires-Dist: requests (==2.26.0)
Requires-Dist: slackclient (==2.9.3)
Requires-Dist: adaptavist (==2.0.0)
